policyengine_uk/__init__.py
policyengine_uk/entities.py
policyengine_uk/microsimulation.py
policyengine_uk/model_api.py
policyengine_uk/modelled_policies.yaml
policyengine_uk/simulation.py
policyengine_uk/system.py
policyengine_uk/tax_benefit_system.py
policyengine_uk/data/__init__.py
policyengine_uk/data/dataset_schema.py
policyengine_uk/data/economic_assumptions.py
policyengine_uk/data/filter_dataset.py
policyengine_uk/data/uprating_indices.yaml
policyengine_uk/dynamics/labour_supply.py
policyengine_uk/dynamics/participation.py
policyengine_uk/dynamics/progression.py
policyengine_uk/parameters/gov/README.md
policyengine_uk/parameters/gov/benefit_uprating_cpi.yaml
policyengine_uk/parameters/gov/boe/base_rate.yaml
policyengine_uk/parameters/gov/boe/index.yaml
policyengine_uk/parameters/gov/contrib/README.md
policyengine_uk/parameters/gov/contrib/abolish_council_tax.yaml
policyengine_uk/parameters/gov/contrib/abolish_state_pension.yaml
policyengine_uk/parameters/gov/contrib/create_private_pension_uprating.py
policyengine_uk/parameters/gov/contrib/freeze_pension_credit.yaml
policyengine_uk/parameters/gov/contrib/behavioral_responses/employee_salary_sacrifice_reduction_rate.yaml
policyengine_uk/parameters/gov/contrib/behavioral_responses/salary_sacrifice_broad_base_haircut_rate.yaml
policyengine_uk/parameters/gov/contrib/benefit_uprating/README.md
policyengine_uk/parameters/gov/contrib/benefit_uprating/all.yaml
policyengine_uk/parameters/gov/contrib/benefit_uprating/non_sp.yaml
policyengine_uk/parameters/gov/contrib/cec/README.md
policyengine_uk/parameters/gov/contrib/cec/non_primary_residence_wealth_tax.yaml
policyengine_uk/parameters/gov/contrib/cec/state_pension_increase.yaml
policyengine_uk/parameters/gov/contrib/conservatives/cb_hitc_household.yaml
policyengine_uk/parameters/gov/contrib/conservatives/pensioner_personal_allowance.yaml
policyengine_uk/parameters/gov/contrib/cps/README.md
policyengine_uk/parameters/gov/contrib/cps/marriage_tax_reforms/README.md
policyengine_uk-2.72.3.dist-info/METADATA
policyengine_uk-2.72.3.dist-info/WHEEL
policyengine_uk-2.72.3.dist-info/licenses/LICENSE
policyengine_uk-2.72.3.dist-info/RECORD
