Metadata-Version: 2.4
Name: policyengine-uk
Version: 2.72.3
Summary: PolicyEngine tax and benefit system for the UK.
Project-URL: Homepage, https://github.com/PolicyEngine/policyengine-uk
Project-URL: Repository, https://github.com/PolicyEngine/policyengine-uk
Project-URL: Issues, https://github.com/PolicyEngine/policyengine-uk/issues
Project-URL: Changelog, https://github.com/PolicyEngine/policyengine-uk/blob/master/CHANGELOG.md
Author-email: PolicyEngine <nikhil@policyengine.org>
Maintainer-email: Nikhil Woodruff <nikhil@policyengine.org>
License-Expression: AGPL-3.0
License-File: LICENSE
Keywords: benefit,microsimulation,social,tax
Classifier: Development Status :: 5 - Production/Stable
Classifier: License :: OSI Approved :: GNU Affero General Public License v3
Classifier: Operating System :: POSIX
Classifier: Programming Language :: Python
Classifier: Programming Language :: Python :: 3.10
Classifier: Programming Language :: Python :: 3.11
Classifier: Programming Language :: Python :: 3.12
Classifier: Programming Language :: Python :: 3.13
Classifier: Topic :: Scientific/Engineering :: Information Analysis
Requires-Python: <3.14,>=3.13
Requires-Dist: microdf-python>=1.2.1
Requires-Dist: policyengine-core>=3.23.6
Requires-Dist: pydantic>=2.11.7
Requires-Dist: tables>=3.10.2
Provides-Extra: dev
Requires-Dist: black; extra == 'dev'
Requires-Dist: coverage; extra == 'dev'
Requires-Dist: furo<2023; extra == 'dev'
Requires-Dist: jupyter-book>=2.0.0a0; extra == 'dev'
Requires-Dist: linecheck; extra == 'dev'
Requires-Dist: pytest; extra == 'dev'
Requires-Dist: pytest-cov; extra == 'dev'
Requires-Dist: rich; extra == 'dev'
Requires-Dist: setuptools; extra == 'dev'
Requires-Dist: snowballstemmer<3,>=2; extra == 'dev'
Requires-Dist: sphinx-argparse<1,>=0.3.2; extra == 'dev'
Requires-Dist: sphinx-math-dollar<2,>=1.2.1; extra == 'dev'
Requires-Dist: tqdm; extra == 'dev'
Requires-Dist: wheel; extra == 'dev'
Requires-Dist: yaml-changelog>=0.1.7; extra == 'dev'
